optimization/__init__.py
optimization/feature_extraction.py
ga_optimization-0.1.dist-info/LICENSE
ga_optimization-0.1.dist-info/METADATA
ga_optimization-0.1.dist-info/WHEEL
ga_optimization-0.1.dist-info/top_level.txt
ga_optimization-0.1.dist-info/RECORD
