Metadata-Version: 2.1
Name: ga-optimization
Version: 0.1
Summary: A package for genetic algorithm-based feature selection on Random Forest Classifier
Home-page: https://github.com/suraj385/ga_optimization
Author: Suraj Gautam
Author-email: beoingsuraz3385@gmail.com
Classifier: Programming Language :: Python :: 3
Classifier: License :: OSI Approved :: MIT License
Classifier: Operating System :: OS Independent
Requires-Python: >=3.6
License-File: LICENSE
Requires-Dist: pandas
Requires-Dist: numpy
Requires-Dist: scikit-learn
Requires-Dist: deap
